wdb/__init__.py
wdb/__main__.py
wdb/_compat.py
wdb/breakpoint.py
wdb/ext.py
wdb/state.py
wdb/ui.py
wdb/utils.py
wdb-3.1.0.dist-info/DESCRIPTION.rst
wdb-3.1.0.dist-info/METADATA
wdb-3.1.0.dist-info/RECORD
wdb-3.1.0.dist-info/WHEEL
wdb-3.1.0.dist-info/entry_points.txt
wdb-3.1.0.dist-info/metadata.json
wdb-3.1.0.dist-info/top_level.txt
